README.md
pyproject.toml
setup.cfg
twitterobserver/__init__.py
twitterobserver/apiclient.py
twitterobserver/cli.py
twitterobserver/db.py
twitterobserver.egg-info/PKG-INFO
twitterobserver.egg-info/SOURCES.txt
twitterobserver.egg-info/dependency_links.txt
twitterobserver.egg-info/entry_points.txt
twitterobserver.egg-info/requires.txt
twitterobserver.egg-info/top_level.txt