Metadata-Version: 2.1
Name: twitterobserver
Version: 0.0.2
Summary: A package to extract follower data from Twitter api
Home-page: UNKNOWN
License: UNKNOWN
Platform: UNKNOWN
